[
  {
    "op": "add",
    "path": [
      "projectdetail515"
    ],
    "val": {
      "id": "projectdetail515",
      "title": "Boulevard (Dublin Crossing) - Phase 4/5",
      "details": {
        "Planning Application #": "PLPA-2016-00064",
        "Application Type": "Site Development Review and Vesting Tentative Tract Map",
        "Application Submittal Date": "12/05/2016",
        "General Plan Land Use": "Dublin Crossing Specific Plan",
        "Specific Plan Area": "Dublin Crossing Specific Plan",
        "Zoning": "DCPD",
        "Project Area": "40 acres",
        "Applicant": {
          "name": "Joe Guerra, Dublin Crossing LLC/Brookfield Residential",
          "address": "500 La Gonda Way, Suite 100, Danville, CA 94526",
          "phone": "(408) 307-7806"
        },
        "Project Planner": {
          "name": "Amy Million - Principal Planner",
          "phone": "(925) 833-6610",
          "email": "amy.million@dublin.ca.gov"
        }
      },
      "location": "Dublin Boulevard",
      "docs": [],
      "status": "Application Under Review",
      "description": "Phases 4 and 5 of the Boulevard project include 509 units and landscape improvements.",
      "images": [
        {
          "original": "http://dublin-development.icitywork.com/wp-content/uploads/2017/04/4-5-site-plan.jpg",
          "thumbnail": "http://dublin-development.icitywork.com/wp-content/uploads/2017/04/4-5-site-plan-150x150.jpg"
        }
      ],
      "geolocation": {
        "lat": 37.713424,
        "lon": -121.904164,
        "iconName": "dot",
        "title": "Boulevard (Dublin Crossing) - Phase 4/5"
      }
    },
    "projectId": "projectdetail515",
    "timestamp": "1492908897000",
    "type": "developments:add"
  },
  {
    "op": "update",
    "path": [
      "projectdetail515",
      "geolocation",
      "lat"
    ],
    "val": 37.711036,
    "oldVal": 37.713424,
    "projectId": "projectdetail515",
    "timestamp": "1495652949000",
    "type": "developments:update"
  },
  {
    "op": "update",
    "path": [
      "projectdetail515",
      "geolocation",
      "lon"
    ],
    "val": -121.905749,
    "oldVal": -121.904164,
    "projectId": "projectdetail515",
    "timestamp": "1495652949000",
    "type": "developments:update"
  },
  {
    "op": "add",
    "path": [
      "projectdetail515",
      "docs",
      0
    ],
    "val": {
      "name": "April 10, 2018 Planning Commission Staff Report",
      "url": "http://dublinca.iqm2.com/Citizens/FileOpen.aspx?Type=1&ID=1278&Inline=True"
    },
    "projectId": "projectdetail515",
    "timestamp": "1513193626000",
    "type": "developments:add"
  },
  {
    "op": "add",
    "path": [
      "projectdetail515",
      "docs",
      1
    ],
    "val": {
      "name": "May 8, 2018 Planning Commission Staff Report",
      "url": "http://dublinca.iqm2.com/Citizens/FileOpen.aspx?Type=1&ID=1287&Inline=True"
    },
    "projectId": "projectdetail515",
    "timestamp": "1513193626000",
    "type": "developments:add"
  },
  {
    "op": "update",
    "path": [
      "projectdetail515",
      "status"
    ],
    "val": "Pubic Hearing",
    "oldVal": "Application Under Review",
    "projectId": "projectdetail515",
    "timestamp": "1513193626000",
    "type": "developments:update"
  },
  {
    "op": "update",
    "path": [
      "projectdetail515",
      "description"
    ],
    "val": "Phases 4 and 5 of the Boulevard project include 510 units and landscape improvements.",
    "oldVal": "Phases 4 and 5 of the Boulevard project include 509 units and landscape improvements.",
    "projectId": "projectdetail515",
    "timestamp": "1513193626000",
    "type": "developments:update"
  },
  {
    "op": "update",
    "path": [
      "projectdetail515",
      "images",
      0,
      "original"
    ],
    "val": "https://dublin-development.icitywork.com/wp-content/uploads/2017/04/4-5-site-plan.jpg",
    "oldVal": "http://dublin-development.icitywork.com/wp-content/uploads/2017/04/4-5-site-plan.jpg",
    "projectId": "projectdetail515",
    "timestamp": "1513193626000",
    "type": "developments:update"
  },
  {
    "op": "update",
    "path": [
      "projectdetail515",
      "images",
      0,
      "thumbnail"
    ],
    "val": "https://dublin-development.icitywork.com/wp-content/uploads/2017/04/4-5-site-plan-150x150.jpg",
    "oldVal": "http://dublin-development.icitywork.com/wp-content/uploads/2017/04/4-5-site-plan-150x150.jpg",
    "projectId": "projectdetail515",
    "timestamp": "1513193626000",
    "type": "developments:update"
  },
  {
    "op": "update",
    "path": [
      "projectdetail515",
      "status"
    ],
    "val": "Final Action",
    "oldVal": "Pubic Hearing",
    "projectId": "projectdetail515",
    "timestamp": "1537002007000",
    "type": "developments:update"
  },
  {
    "op": "update",
    "path": [
      "projectdetail515",
      "title"
    ],
    "val": "Boulevard (Dublin Crossing) – Phase 4 & 5",
    "oldVal": "Boulevard (Dublin Crossing) - Phase 4/5",
    "projectId": "projectdetail515",
    "timestamp": "1596943340000",
    "type": "developments:update"
  },
  {
    "op": "update",
    "path": [
      "projectdetail515",
      "geolocation",
      "iconName"
    ],
    "val": "building",
    "oldVal": "dot",
    "projectId": "projectdetail515",
    "timestamp": "1596943340000",
    "type": "developments:update"
  },
  {
    "op": "update",
    "path": [
      "projectdetail515",
      "geolocation",
      "title"
    ],
    "val": "Boulevard (Dublin Crossing) – Phase 4 & 5",
    "oldVal": "Boulevard (Dublin Crossing) - Phase 4/5",
    "projectId": "projectdetail515",
    "timestamp": "1596943340000",
    "type": "developments:update"
  },
  {
    "op": "update",
    "path": [
      "projectdetail515",
      "details",
      "Application Type"
    ],
    "val": "Site Development Review Permit and Vesting Tentative Tract Map",
    "oldVal": "Site Development Review and Vesting Tentative Tract Map",
    "projectId": "projectdetail515",
    "timestamp": "1656420658000",
    "type": "developments:update"
  },
  {
    "op": "update",
    "path": [
      "projectdetail515",
      "details",
      "Applicant",
      "name"
    ],
    "val": "Mandi Misasi, Brookfield Residential",
    "oldVal": "Joe Guerra, Dublin Crossing LLC/Brookfield Residential",
    "projectId": "projectdetail515",
    "timestamp": "1656420658000",
    "type": "developments:update"
  },
  {
    "op": "update",
    "path": [
      "projectdetail515",
      "details",
      "Applicant",
      "address"
    ],
    "val": "12657 Alcosta Blvd. Ste 250, San Ramon CA 94563",
    "oldVal": "500 La Gonda Way, Suite 100, Danville, CA 94526",
    "projectId": "projectdetail515",
    "timestamp": "1656420658000",
    "type": "developments:update"
  },
  {
    "op": "update",
    "path": [
      "projectdetail515",
      "details",
      "Applicant",
      "phone"
    ],
    "val": "925-743-8000",
    "oldVal": "(408) 307-7806",
    "projectId": "projectdetail515",
    "timestamp": "1656420658000",
    "type": "developments:update"
  },
  {
    "op": "update",
    "path": [
      "projectdetail515",
      "geolocation",
      "iconName"
    ],
    "val": "home",
    "oldVal": "building",
    "projectId": "projectdetail515",
    "timestamp": "1721851200000",
    "type": "developments:update"
  }
]